{
    "key": "group_67f36cad8c7e3",
    "title": "Template: Investor Centre",
    "fields": [
        {
            "key": "field_67f36cadcb2e0",
            "label": "Hero",
            "name": "",
            "aria-label": "",
            "type": "tab",
            "instructions": "",
            "required": 0,
            "conditional_logic": 0,
            "wrapper": {
                "width": "",
                "class": "",
                "id": ""
            },
            "wpml_cf_preferences": 3,
            "placement": "left",
            "endpoint": 0,
            "selected": 0
        },
        {
            "key": "field_67f36ccccb2e1",
            "label": "Centered Hero",
            "name": "centered-hero",
            "aria-label": "",
            "type": "clone",
            "instructions": "",
            "required": 0,
            "conditional_logic": 0,
            "wrapper": {
                "width": "",
                "class": "",
                "id": ""
            },
            "wpml_cf_preferences": 3,
            "clone": [
                "group_67eb96610c607"
            ],
            "display": "seamless",
            "layout": "block",
            "prefix_label": 0,
            "prefix_name": 0
        },
        {
            "key": "field_67f36d57cb2e2",
            "label": "Full Image",
            "name": "",
            "aria-label": "",
            "type": "tab",
            "instructions": "",
            "required": 0,
            "conditional_logic": 0,
            "wrapper": {
                "width": "",
                "class": "",
                "id": ""
            },
            "wpml_cf_preferences": 3,
            "placement": "left",
            "endpoint": 0,
            "selected": 0
        },
        {
            "key": "field_67f36d67cb2e3",
            "label": "Full Image",
            "name": "full-image",
            "aria-label": "",
            "type": "clone",
            "instructions": "",
            "required": 0,
            "conditional_logic": 0,
            "wrapper": {
                "width": "",
                "class": "",
                "id": ""
            },
            "wpml_cf_preferences": 3,
            "clone": [
                "group_67ebd0bf9dea0"
            ],
            "display": "seamless",
            "layout": "block",
            "prefix_label": 0,
            "prefix_name": 0
        },
        {
            "key": "field_67f36d75cb2e4",
            "label": "Reports",
            "name": "",
            "aria-label": "",
            "type": "tab",
            "instructions": "",
            "required": 0,
            "conditional_logic": 0,
            "wrapper": {
                "width": "",
                "class": "",
                "id": ""
            },
            "wpml_cf_preferences": 3,
            "placement": "left",
            "endpoint": 0,
            "selected": 0
        },
        {
            "key": "field_67f36d83cb2e5",
            "label": "Reports",
            "name": "reports",
            "aria-label": "",
            "type": "clone",
            "instructions": "",
            "required": 0,
            "conditional_logic": 0,
            "wrapper": {
                "width": "",
                "class": "",
                "id": ""
            },
            "wpml_cf_preferences": 3,
            "clone": [
                "group_67f36befa83e4"
            ],
            "display": "seamless",
            "layout": "block",
            "prefix_label": 0,
            "prefix_name": 0
        },
        {
            "key": "field_67f36d96cb2e6",
            "label": "Members",
            "name": "",
            "aria-label": "",
            "type": "tab",
            "instructions": "",
            "required": 0,
            "conditional_logic": 0,
            "wrapper": {
                "width": "",
                "class": "",
                "id": ""
            },
            "wpml_cf_preferences": 3,
            "placement": "left",
            "endpoint": 0,
            "selected": 0
        },
        {
            "key": "field_67f36da0cb2e7",
            "label": "Members",
            "name": "members",
            "aria-label": "",
            "type": "clone",
            "instructions": "",
            "required": 0,
            "conditional_logic": 0,
            "wrapper": {
                "width": "",
                "class": "",
                "id": ""
            },
            "wpml_cf_preferences": 3,
            "clone": [
                "group_67ed40acc4d45"
            ],
            "display": "seamless",
            "layout": "block",
            "prefix_label": 0,
            "prefix_name": 0
        },
        {
            "key": "field_67f37a2d109b3",
            "label": "Contact Us",
            "name": "",
            "aria-label": "",
            "type": "tab",
            "instructions": "",
            "required": 0,
            "conditional_logic": 0,
            "wrapper": {
                "width": "",
                "class": "",
                "id": ""
            },
            "wpml_cf_preferences": 3,
            "placement": "left",
            "endpoint": 0,
            "selected": 0
        },
        {
            "key": "field_67f37a46109b4",
            "label": "Contact Us",
            "name": "contact-form",
            "aria-label": "",
            "type": "clone",
            "instructions": "",
            "required": 0,
            "conditional_logic": 0,
            "wrapper": {
                "width": "",
                "class": "",
                "id": ""
            },
            "wpml_cf_preferences": 3,
            "clone": [
                "group_67efd08997f84"
            ],
            "display": "seamless",
            "layout": "block",
            "prefix_label": 0,
            "prefix_name": 0
        },
        {
            "key": "field_67f37a6c109b5",
            "label": "Practices",
            "name": "",
            "aria-label": "",
            "type": "tab",
            "instructions": "",
            "required": 0,
            "conditional_logic": 0,
            "wrapper": {
                "width": "",
                "class": "",
                "id": ""
            },
            "wpml_cf_preferences": 3,
            "placement": "left",
            "endpoint": 0,
            "selected": 0
        },
        {
            "key": "field_67f37a88109b6",
            "label": "Practices",
            "name": "practices",
            "aria-label": "",
            "type": "clone",
            "instructions": "",
            "required": 0,
            "conditional_logic": 0,
            "wrapper": {
                "width": "",
                "class": "",
                "id": ""
            },
            "wpml_cf_preferences": 3,
            "clone": [
                "group_67f37957e8ba7"
            ],
            "display": "seamless",
            "layout": "block",
            "prefix_label": 0,
            "prefix_name": 0
        },
        {
            "key": "field_690ca944bf92f",
            "label": "FAQ",
            "name": "",
            "aria-label": "",
            "type": "tab",
            "instructions": "",
            "required": 0,
            "conditional_logic": 0,
            "wrapper": {
                "width": "",
                "class": "",
                "id": ""
            },
            "wpml_cf_preferences": 3,
            "placement": "top",
            "endpoint": 0,
            "selected": 0
        },
        {
            "key": "field_690ca951bf930",
            "label": "FAQ Secondary",
            "name": "faq-secondary",
            "aria-label": "",
            "type": "clone",
            "instructions": "",
            "required": 0,
            "conditional_logic": 0,
            "wrapper": {
                "width": "",
                "class": "",
                "id": ""
            },
            "wpml_cf_preferences": 3,
            "clone": [
                "group_690ca62e8d4cc"
            ],
            "display": "seamless",
            "layout": "block",
            "prefix_label": 0,
            "prefix_name": 0
        }
    ],
    "location": [
        [
            {
                "param": "page_template",
                "operator": "==",
                "value": "template-pages\/investor-centre.php"
            }
        ]
    ],
    "menu_order": 0,
    "position": "normal",
    "style": "default",
    "label_placement": "top",
    "instruction_placement": "label",
    "hide_on_screen": "",
    "active": true,
    "description": "",
    "show_in_rest": 0,
    "display_title": "",
    "acfml_field_group_mode": "advanced",
    "modified": 1762437486
}
